ssheval.py
ssheval-0.1.0a0.dist-info/licenses/LICENSE
ssheval-0.1.0a0.dist-info/METADATA
ssheval-0.1.0a0.dist-info/WHEEL
ssheval-0.1.0a0.dist-info/top_level.txt
ssheval-0.1.0a0.dist-info/RECORD
