Metadata-Version: 2.4
Name: ssheval
Version: 0.1.0a0
Summary: A cross-platform pure Python script for executing remote commands over SSH and streaming raw stdout/stderr.
Author-email: Jifeng Wu <jifengwu2k@gmail.com>
License-Expression: MIT
Project-URL: Homepage, https://github.com/jifengwu2k/ssheval
Project-URL: Bug Tracker, https://github.com/jifengwu2k/ssheval/issues
Classifier: Programming Language :: Python :: 2
Classifier: Programming Language :: Python :: 3
Classifier: Operating System :: OS Independent
Requires-Python: >=2
License-File: LICENSE
Requires-Dist: paramiko
Dynamic: license-file
